__init__.py
hello.py
onda-0.0.0.dist-info/METADATA
onda-0.0.0.dist-info/WHEEL
onda-0.0.0.dist-info/top_level.txt
onda-0.0.0.dist-info/RECORD
